{
  "timestamp_utc": "20260605-184750-687913",
  "command": "auto-distribution",
  "status": "ok",
  "steps": [
    {
      "step": "auto-distribution",
      "command": [
        "C:\\Python313\\python.exe",
        "D:\\AgentesGuille\\agente_browser_cdp.py",
        "auto-distribution",
        "--channels",
        "all",
        "--limit",
        "18",
        "--per-channel",
        "3"
      ],
      "started_utc": "20260605-184700-635095",
      "finished_utc": "20260605-184750-687662",
      "returncode": 0,
      "status": "ok"
    }
  ]
}
